hello/__init__.py
hello/vietnamese.py
tung-0.1.dist-info/DESCRIPTION.rst
tung-0.1.dist-info/METADATA
tung-0.1.dist-info/RECORD
tung-0.1.dist-info/WHEEL
tung-0.1.dist-info/metadata.json
tung-0.1.dist-info/top_level.txt
